{
    "$schema": "https://github.com/ManualForArchipelago/Manual/raw/main/schemas/Manual.items.schema.json",
    "data": [
        {
            "name": "Progressive Cycle",
            "category": [
                "Cycle Locks"
            ],
            "count": 7,
            "progression": true
        },
        {
            "name": "Points",
            "category": [
                "Filler"
            ],
            "count": 100,
            "filler": true
        },
        {
            "name": "Soundscan Medal",
            "category": [
                "Soundscan Medal"
            ],
            "count": 38,
            "useful": true,
            "_comment": "All maps up to Sunrise Showdown accounted for. Added and extra 5 because I don't know how many the NOISZ scan has"
        },
        {
            "name": "grode",
            "category": [
                "Chapter 1 Songs"
            ],
            "progression": true
        },
        {
            "name": "Tavgha",
            "category": [  
                "Chapter 1 Songs"
            ],
            "progression": true
        },
        {
            "name": "Fixation Towards the Stars",
            "category": [ 
                "Chapter 1 Songs",
                "Bedroom Playlist"
            ],
            "progression": true
        },
        {
            "name": "Signals Afar",
            "category": [                
                "Chapter 1 Songs"
            ],
            "progression": true
        },
        {
            "name": "QUASAR",
            "category": [               
                "Chapter 1 Songs",
                "Living Room Playlist"
            ],
            "progression": true
        },
        {
            "name": "septima",
            "category": [ 
                "Chapter 1 Songs",
                "Living Room Playlist"
            ],
            "progression": true
        },
        {
            "name": "Chronomia",
            "category": [ 
                "Chapter 1 Songs"
            ],
            "progression": true
        },
        {
            "name": "Macropolis",
            "category": [
                "Chapter 1 Songs"
            ],
            "progression": true
        },
        {
            "name": "Happy Go Lucky!!!",
            "category": [
                "Shop Songs",
                "Living Room Playlist"
            ],
            "progression": true
        },
        {
            "name": "obair-gheris",
            "category": [
                "Chapter 1 Songs",
                "Bedroom Playlist"
            ],
            "progression": true
        },
        {
            "name": "PYROMANIA",
            "category": [
                "Bosses"
            ],
            "progression": true
        },
        {
            "name": "Cosmogryal",
            "category": [
                "Chapter 2 Songs",
                "Living Room Playlist"
            ],
            "progression": true
        },
        {
            "name": "Courage",
            "category": [
                "Chapter 2 Songs"
            ],
            "progression": true
        },
        {
            "name": "POISON GARDEN",
            "category": [
                "Chapter 2 Songs"
            ],
            "progression": true
        },
        {
            "name": "APO11O",
            "category": [
                "Chapter 2 Songs"
            ],
            "progression": true
        },
        {
            "name": "safe_state",
            "category": [
                "Shop Songs",
                "Living Room Playlist"
            ],
            "progression": true
        },
        {
            "name": "Prime",
            "category": [
                "Chapter 2 Songs",
                "Living Room Playlist"
            ],
            "progression": true
        },
        {
            "name": "Revelation",
            "category": [
                "Chapter 2 Songs"
            ],
            "progression": true
        },
        {
            "name": "Chronoexplorers",
            "category": [
                "Chapter 2 Songs",
                "Kitchen Playlist"
            ],
            "progression": true
        },
        {
            "name": "Octava",
            "category": [
                "Chapter 2 Songs",
                "Living Room Playlist"
            ],
            "progression": true
        },
        {
            "name": "BPM",
            "category": [
                "Chapter 3 Songs"
            ],
            "progression": true
        },
        {
            "name": "valor/starcross",
            "category": [
                "Bosses"
            ],
            "progression": true
        },
        {
            "name": "Unraveling Stasis",
            "category": [
                "Bosses"
            ],
            "progression": true
        },
        {
            "name": "Ione",
            "category": [
                "Chapter 3 Songs"
            ],
            "progression": true
        },
        {
            "name": "UTF-8000000000",
            "category": [
                "Chapter 3 Songs",
                "Bedroom Playlist"
            ],
            "progression": true
        },
        {
            "name": "Dear My Endsummer",
            "category": [
                "Chapter 3 Songs",
                "Living Room Playlist"
            ],
            "progression": true
        },
        {
            "name": "Cyclical Rebellion",
            "category": [
                "Chapter 3 Songs",
                "Bedroom Playlist"
            ],
            "progression": true
        },
        {
            "name": "Angel's Window",
            "category": [
                "Chapter 3 Songs",
                "Kitchen Playlist"
            ],
            "progression": true
        },
        {
            "name": "ANARCHIC LIGHT",
            "category": [
                "Chapter 3 Songs",
                "Kitchen Playlist"
            ],
            "progression": true
        },
        {
            "name": "Singularity",
            "category": [
                "Chapter 3 Songs"
            ],
            "progression": true
        },
        {
            "name": "Simulated Reality",
            "category": [
                "Chapter 3 Songs"
            ],
            "progression": true
        },
        {
            "name": "Aleph-0",
            "category": [
                "Chapter 4 Songs",
                "Kitchen Playlist"
            ],
            "progression": true
        },
        {
            "name": "SUPERNOVA",
            "category": [
                "Bosses"
            ],
            "progression": true
        },
        {
            "name": "Acolyte",
            "category": [
                "Shop Songs"
            ],
            "progression": true
        },
        {
            "name": "Lost City",
            "category": [
                "Shop Songs",
                "Living Room Playlist"
            ],
            "progression": true
        },
        
        {
            "name": "F1055",
            "category": [
                "Shop Songs"
            ],
            "progression": true
        },
        {
            "name": "Doppelganger",
            "category": [
                "Chapter 3 Songs",
                "Kitchen Playlist"
            ],
            "progression": true
        },
        {
            "name": "Gems",
            "category": [
                "Filler"
            ],
            "count": 63,
            "filler": true,
            "_comment": "based off location count, not total in the whole game"
        },
        {
            "name": "Tormented World",
            "category": [
                "Chapter 3 Songs"
            ],
            "progression": true
        },
        {
            "name": "Ops Limone",
            "category": [
                "Chapter 3 Songs",
                "Kitchen Playlist"
            ],
            "progression": true
        },
        {
            "name": "Seraphiel",
            "category": [
                "Chapter 3 Songs",
                "Bedroom Playlist"
            ],
            "progression": true
        },
        {
            "name": "INFiNiTE ENERZY -Overdoze-",
            "category": [
                "Shop Songs"
            ],
            "progression": true
        },
        {
            "name": "hotline_ophiucus",
            "category": [
                "Chapter 4 Songs"
            ],
            "progression": true
        },
        {
            "name": "execution_program",
            "category": [
                "Bosses",
                "Bedroom Playlist"
            ],
            "progression": true
        },
        {
            "name": "grode decoherence",
            "category": [
                "Shop Songs",
                "Living Room Playlist"
            ],
            "progression": true
        },
        {
            "name": "MARENOL",
            "category": [
                "Chapter 3 Songs"
            ],
            "progression": true
            
        },
        {
            "name": "STARGAZERS",
            "category": [
                "Chapter 4 Songs"
            ],
            "progression": true
        },
        {
            "name": "Landing Key - The Last Page",
            "category": [
                "Final Landing",
                "Landing Keys"
            ],
            "progression": true
        },
        {
            "name": "The Last Page",
            "category": [
                "Final Landing",
                "Living Room Playlist"
            ],
            "progression": true
        }, 
        {
            "name": "CandyCracker",
            "category": [
                "Final Landing",
                "Living Room Playlist"
            ],
            "progression": true
        },
        {
            "name": "Landing Key - CandyCracker",
            "category": [
                "Final Landing",
                "Landing Keys"
            ],
            "progression": true
        },
        {
            "name": "Orphen",
            "category": [
                "Final Landing",
                "Bedroom Playlist"
            ],
            "progression": true
        },
        {
            "name": "Landing Key - Orphen",
            "category": [
                "Final Landing",
                "Landing Keys"
            ],
            "progression": true
        },
        {
            "name": "3.1V.C1",
            "category": [
                "Final Landing",
                "Kitchen Playlist"
            ],
            "progression": true
        },
        {
            "name": "Landing Key - 3.1V.C1",
            "category": [
                "Final Landing",
                "Landing Keys"
            ],
            "progression": true
        },
        {
            "name": "ASTELLION",
            "category": [
                "Final Landing"
            ],
            "progression": true
        },
        {
            "name": "TVO Miracle",
            "category": [
                "TVO Interventions"
            ],
            "progression": true
        },
        {
            "name": "Last Wish",
            "category": [
                "Bosses"
            ],
            "progression": true,
            "requires": "|SUPERNOVA|"
        },
        {
            "name": "CLAUDIA -estella-",
            "category": [
                "Chapter 3 Songs",
                "Bedroom Playlist"
            ],
            "progression": true
        },
        {
            "name": "Shattered Sky After Rain",
            "category": [
                "Chapter 5 Songs",
                "Living Room Playlist"
            ],
            "progression": true
        },
        {
            "name": "exterminate",
            "category": [
                "Chapter 5 Songs",
                "Bedroom Playlist"
            ],
            "progression": true
        },
        {
            "name": "The Night of Fright",
            "category": [
                "Chapter 5 Songs",
                "Kitchen Playlist"
            ],
            "progression": true
        },
        {
            "name": "nullbreak",
            "category": [
                "Chapter 5 Songs",
                "Bedroom Playlist"
            ],
            "progression": true
        },
        {
            "name": "Nhlev",
            "category": [
                "Chapter 5 Songs"
            ],
            "progression": true
        },
        {
            "name": "Sternstrude",
            "category": [
                "Chapter 5 Songs",
                "Living Room Playlist"
            ],
            "progression": true
        },
        {
            "name": "CLAUDIA -libertia-",
            "category": [
                "Boss"
            ],
            "progression": true
        },
        {
            "name": "stop-motion",
            "category": [
                "Boss"
            ],
            "progression": true
        },
        {
            "name": "SENTINEL",
            "category": [
                "Boss"
            ],
            "progression": true
        },
        {
            "name": "the more i carry on...",
            "category": [
                "Chapter 6 Songs"
            ],
            "progression": true
        },
        {
            "name": "lost contact",
            "category": [
                "Chapter 5 Songs"
            ],
            "progression": true
        },
        {
            "name": "stardust",
            "category": [
                "Chapter 6 Songs",
                "Living Room Playlist"
            ],
            "progression": true
        },
        {
            "name": "final farewell -aquaregia-",
            "category": [
                "Chapter 6 Songs"
            ],
            "progression": true
        },
        {
            "name": "Prismatic Vortex",
            "category": [
                "Chapter 6 Songs",
                "Kitchen Playlist"
            ],
            "progression": true
        },
        {
            "name": "heptagramme",
            "category": [
                "Chapter 6 Songs",
                "Bedroom Playlist"
            ],
            "progression": true
        },
        {
            "name": "execute.",
            "category": [
                "Chapter 6 Songs"
            ],
            "progression": true
        },
        {
            "name": "even at the end of the world, you left it",
            "category": [
                "Chapter 6 Songs",
                "Bedroom Playlist"
            ],
            "progression": true
        },
        {
            "name": "Memory Bank",
            "category": [
                "TVO Interventions"
            ],
            "progression": true
        },
        {
            "name": "Reboot",
            "category": [
                "Chapter 6 Songs",
                "Kitchen Playlist"
            ],
            "progression": true
        },
        {
            "name": "Nightshade",
            "category": [
                "Chapter 6 Songs",
                "Kitchen Playlist"
            ],
            "progression": true
        },
        {
            "name": "crack in the earth",
            "category": [
                "Chapter 6 Songs"
            ],
            "progression": true
        },
        {
            "name": "Concrete Jungle",
            "category": [
                "Chapter 6 Songs"
            ],
            "progression": true
        },
        {
            "name": "aria of ruinated winds",
            "category": [
                "Chapter 6 Songs",
                "Bedroom Playlist"
            ],
            "progression": true
        },
        {
            "name": "ULTIMATUM",
            "category": [
                "Chapter 6 Songs"
            ],
            "progression": true
        },
        {
            "name": "CONVERGENCE",
            "category": [
                "Bosses"
            ],
            "progression": true
        },
        {
            "name": "thrinos;pygmalion",
            "category": [
                "Bosses"
            ],
            "progression": true
        },
        {
            "name": "Bloom in Two",
            "category": [
                "Bosses"
            ],
            "progression": true
        },
        {
            "name": "Unknown Absolute",
            "category": [
                "Bosses"
            ],
            "progression": true
        },
        {
            "name": "First Breath",
            "category": [
                "Bosses"
            ],
            "progression": true
        },
        {
            "name": "SELF",
            "category": [
                "Bosses"
            ],
            "progression": true
        },
        {
            "name": "acta est fabula, plaudite",
            "category": [
                "Bosses"
            ],
            "progression": true
        },
        {
            "name": "There",
            "category": [
                "Shop Songs"
            ],
            "progression": true
        },
        {
            "name": "Options",
            "category": [
                "Shop Songs"
            ],
            "progression": true
        },
        {
            "name": "Crosshatch",
            "category": [
                "Chapter 1 Songs"
            ],
            "progression": true
        },
        {
            "name": "Credits",
            "category": [
                "Shop Songs"
            ],
            "progression": true
        },
        {
            "name": "tenpo pakala",
            "category": [
                "Chapter 2 Songs"
            ],
            "progression": true
        },
        {
            "name": "The 89's Momentum",
            "category": [
                "Shop Songs"
            ],
            "progression": true
        },
        {
            "name": "BADSECRET",
            "category": [
                "Shop Songs"
            ],
            "progression": true
        },
        {
            "name": "GOODRAGE",
            "category": [
                "Shop Songs"
            ],
            "progression": true
        },
        {
            "name": "-1",
            "category": [
                "Shop Songs",
                "Kitchen Playlist"
            ],
            "progression": true
        },
        {
            "name": "3, 2, 1, Let's Go",
            "category": [
                "Shop Songs"
            ],
            "progression": true
        },
        {
            "name": "Asymmetry - takehirotei remix",
            "category": [
                "Shop Songs"
            ],
            "progression": true
        },
        {
            "name": "Avalon",
            "category": [
                "Chapter 3 Songs"
            ],
            "progression": true
        },
        {
            "name": "Beyond the Heart - Broken Heart Mix",
            "category": [
                "Shop Songs"
            ],
            "progression": true
        },
        {
            "name": "Crimson Dance - vivid/stasis Edit",
            "category": [
                "Chapter 5"
            ],
            "progression": true
        },
        {
            "name": "ENERGY SYNERGY MATRIX",
            "category": [
                "Chapter 1 Songs"
            ],
            "progression": true
        },
        {
            "name": "energy trixxx",
            "category": [
                "Chapter 1 Songs"
            ],
            "progression": true
        },
        {
            "name": "FULi AUTO BUSTER",
            "category": [
                "Shop Songs"
            ],
            "progression": true
        },
        {
            "name": "FULi AUTO SHOOTER",
            "category": [
                "Shop Songs"
            ],
            "progression": true
        },
        {
            "name": "Farewell to Syzygia",
            "category": [
                "Chapter 2 Songs",
                "Bedroom Playlist"
            ],
            "progression": true
        },
        {
            "name": "G e n g a o z o",
            "category": [
                "Shop Songs"
            ],
            "progression": true
        },
        {
            "name": "Gauntlet",
            "category": [
                "Shop Songs"
            ],
            "progression": true
        },
        {
            "name": "grode - Wyvren's Remix",
            "category": [
                "Shop Songs"
            ],
            "progression": true
        },
        {
            "name": "Foolish Ambition",
            "category": [
                "Shop Songs"
            ],
            "progression": true
        },
        {
            "name": "HTTPS",
            "category": [
                "Shop Songs"
            ],
            "progression": true
        },
        {
            "name": "LET THE CREATION BEGIN",
            "category": [
                "Shop Songs"
            ],
            "progression": true
        },
        {
            "name": "Luminaria",
            "category": [
                "Shop Songs"
            ],
            "progression": true
        },
        {
            "name": "MYSTERIOUS TRIGGER",
            "category": [
                "Shop Songs"
            ],
            "progression": true
        },
        {
            "name": "Perfect ConfeCute!!",
            "category": [
                "Shop Songs"
            ],
            "progression": true
        },
        {
            "name": "Pictured as Perfect",
            "category": [
                "Shop Songs"
            ],
            "progression": true
        },
        {
            "name": "Random",
            "category": [
                "Shop Songs"
            ],
            "progression": true
        },
        {
            "name": "slic.hertz",
            "category": [
                "Shop Songs"
            ],
            "progression": true
        },
        {
            "name": "Spell Diver",
            "category": [
                "Shop Songs"
            ],
            "progression": true
        },
        {
            "name": "Spin Cycle - NETCAVY ReMiX",
            "category": [
                "Shop Songs"
            ],
            "progression": true
        },
        {
            "name": "Showdown",
            "category": [
                "Shop Songs"
            ],
            "progression": true
        },
        {
            "name": "Stellaria",
            "category": [
                "Shop Songs"
            ],
            "progression": true
        },
        {
            "name": "Synthesizer Party",
            "category": [
                "Shop Songs"
            ],
            "progression": true
        },
        {
            "name": "taffy",
            "category": [
                "Shop Songs"
            ],
            "progression": true
        },
        {
            "name": "TERABYTE CONNECTION",
            "category": [
                "Shop Songs"
            ],
            "progression": true
        },
        {
            "name": "The Next Arcady",
            "category": [
                "Shop Songs"
            ],
            "progression": true
        },
        {
            "name": "Un-TECHNiCAL Reason",
            "category": [
                "Shop Songs"
            ],
            "progression": true
        },
        {
            "name": "WATAGASHI RUSH",
            "category": [
                "Shop Songs"
            ],
            "progression": true
        },
        {
            "name": "What You Love",
            "category": [
                "Shop Songs"
            ],
            "progression": true
        },
        {
            "name": "Yamai",
            "category": [
                "Shop Songs"
            ],
            "progression": true
        },
        {
            "name": "NULCTRL",
            "category": [
                "Soundscan Maps"
            ],
            "progression": true
        },
        {
            "name": "Trip Coffee",
            "category": [
                "Soundscan Maps"
            ],
            "progression": true
        },
        {
            "name": "ULTIMATE",
            "category": [
                "Soundscan Maps"
            ],
            "progression": true
        },
        {
            "name": "Rafflesia",
            "category": [
                "Soundscan Maps"
            ],
            "progression": true
        },
        {
            "name": "Sanzui",
            "category": [
                "Soundscan Maps"
            ],
            "progression": true
        },
        {
            "name": "WAVE PUNCH",
            "category": [
                "Soundscan Maps"
            ],
            "progression": true
        },
        {
            "name": "Luminous Entities Lost Heart",
            "category": [
                "Soundscan Maps"
            ],
            "progression": true
        },
        {
            "name": "Proper Rhythm",
            "category": [
                "Soundscan Maps"
            ],
            "progression": true
        },
        {
            "name": "WORN OUT TAPES [tally-ho! version]",
            "category": [
                "Soundscan Maps"
            ],
            "progression": true
        },
        {
            "name": "All The Times",
            "category": [
                "Soundscan Maps"
            ],
            "progression": true
        },
        {
            "name": "It Go - Cheryl Stelli Remix",
            "category": [
                "Soundscan Maps"
            ],
            "progression": true
        },
        {
            "name": "LORELEI",
            "category": [
                "Soundscan Maps"
            ],
            "progression": true
        },
        {
            "name": "Faux Real - VIVID REDUX",
            "category": [
                "Soundscan Maps"
            ],
            "progression": true
        },
        {
            "name": "CITY RIDE IN THE JUNGLE",
            "category": [
                "Soundscan Maps"
            ],
            "progression": true
        },
        {
            "name": "Battle in Ememy Territory",
            "category": [
                "Soundscan Maps"
            ],
            "progression": true
        },
        {
            "name": "Star Dream -Millenium Version-",
            "category": [
                "Soundscan Maps"
            ],
            "progression": true
        },
        {
            "name": "Secret Illumination",
            "category": [
                "Soundscan Maps"
            ],
            "progression": true
        },
        {
            "name": "MVURBD",
            "category": [
                "Soundscan Maps"
            ],
            "progression": true
        },
        {
            "name": "IGNITED",
            "category": [
                "Soundscan Maps"
            ],
            "progression": true
        },
        {
            "name": "Etiquette",
            "category": [
                "Soundscan Maps"
            ],
            "progression": true
        },
        {
            "name": "Dreams From Another World",
            "category": [
                "Soundscan Maps"
            ],
            "progression": true
        },
        {
            "name": "micro.wav",
            "category": [
                "Soundscan Maps"
            ],
            "progression": true
        },
        {
            "name": "Rrhar'il",
            "category": [
                "Soundscan Maps"
            ],
            "progression": true
        },
        {
            "name": "Distorted Fate",
            "category": [
                "Soundscan Maps"
            ],
            "progression": true
        },
        {
            "name": "Benighted Rewaking",
            "category": [
                "Soundscan Maps"
            ],
            "progression": true
        },
        {
            "name": "Images",
            "category": [
                "Soundscan Maps"
            ],
            "progression": true
        },
        {
            "name": "MULTIPHEX",
            "category": [
                "Soundscan Maps"
            ],
            "progression": true
        },
        {
            "name": "Luxinvore",
            "category": [
                "Sunrise Showdown"
            ],
            "progression": true
        },
        {
            "name": "Synthesis",
            "category": [
                "Sunrise Showdown"
            ],
            "progression": true
        },
        {
            "name": "When the Dragon Falls",
            "category": [
                "Sunrise Showdown"
            ],
            "progression": true
        },
        {
            "name": "And So You Felt",
            "category": [
                "Sunrise Showdown"
            ],
            "progression": true
        },
        {
            "name": "3c",
            "category": [
                "Sunrise Showdown"
            ],
            "progression": true,
            "_comment": "I wish I could use colons"
        },
        {
            "name": "Surtrs Wish",
            "category": [
                "Sunrise Showdown"
            ],
            "progression": true
        },
        {
            "name": "APOCALYPSE CALL",
            "category": [
                "Sunrise Showdown"
            ],
            "progression": true
        },
        {
            "name": "Void Lens",
            "category": [
                "Hidden Landing Access"
            ],
            "progression": true
        },
        {
            "name": "Attractor Force",
            "category": [
                "Hidden Landing"
            ],
            "progression": true
        },
        {
            "name": "See You Move",
            "category": [
                "Hidden Landing"
            ],
            "progression": true
        },
        {
            "name": "Voltage Strike",
            "category": [
                "Hidden Landing"
            ],
            "progression": true
        },
        {
            "name": "refract dense",
            "category": [
                "Hidden Landing"
            ],
            "progression": true
        },
        {
            "name": "B3611V",
            "category": [
                "Hidden Landing"
            ],
            "progression": true
        },
        {
            "name": "Tamasatchi Egg",
            "category": [
                "Backstage Access"
            ],
            "progression": true
        },
        {
            "name": "Solomons Seal",
            "category": [
                "Backstage Access"
            ],
            "progression": true
        }
    ]

}